sqtom/__init__.py
sqtom/_version.py
sqtom/fitting_1d.py
sqtom/fitting_2d.py
sqtom/forward_solver.py
sqtom-0.4.0.dist-info/LICENSE
sqtom-0.4.0.dist-info/METADATA
sqtom-0.4.0.dist-info/WHEEL
sqtom-0.4.0.dist-info/top_level.txt
sqtom-0.4.0.dist-info/RECORD
